setup.py
gintonic/__init__.py
gintonic.egg-info/PKG-INFO
gintonic.egg-info/SOURCES.txt
gintonic.egg-info/dependency_links.txt
gintonic.egg-info/not-zip-safe
gintonic.egg-info/top_level.txt