Metadata-Version: 1.0
Name: gintonic
Version: 0.1
Summary: stock API
Home-page: https://github.com/shbook/gintonic
Author: sharebook
Author-email: sharebook@outlook.kr
License: GPL
Platform: UNKNOWN
